Demo/PWM_Demo.py
OPi/GPIO.py
OPi/__init__.py
OPi/constants.py
OPi/event.py
OPi/pin_mappings.py
OPi/sysfs.py
nanopi/__init__.py
nanopi/duo.py
nanopi/m4.py
nanopi/neocore2.py
orangepi/__init__.py
orangepi/i96.py
orangepi/lite.py
orangepi/lite2.py
orangepi/one.py
orangepi/oneplus.py
orangepi/pc.py
orangepi/pc2.py
orangepi/pcplus.py
orangepi/pi3.py
orangepi/pi4.py
orangepi/pi4B.py
orangepi/plus2e.py
orangepi/prime.py
orangepi/r1.py
orangepi/winplus.py
orangepi/zero.py
orangepi/zero2.py
orangepi/zero3.py
orangepi/zeroplus.py
orangepi/zeroplus2.py
radxa/__init__.py
radxa/zero.py
rockpi/__init__.py
rockpi/s.py
opi_gpio_picoplanetdev-0.5.4.dist-info/METADATA
opi_gpio_picoplanetdev-0.5.4.dist-info/WHEEL
opi_gpio_picoplanetdev-0.5.4.dist-info/licenses/LICENSE
opi_gpio_picoplanetdev-0.5.4.dist-info/RECORD
