Metadata-Version: 2.1
Name: OPi.GPIO_PicoPlanetDev
Version: 0.5.4
Summary: Drop-in replacement for RPi.GPIO supporting Orange Pi and other SBCs
Project-URL: Homepage, https://github.com/PicoPlanetDev/OPi.GPIO
Project-URL: Bug Tracker, https://github.com/PicoPlanetDev/OPi.GPIO/issues
Author-email: Sigmond Kukla <picoplanetdev@gmail.com>
License-File: LICENSE
Classifier: License :: OSI Approved :: MIT License
Classifier: Operating System :: POSIX :: Linux
Classifier: Programming Language :: Python :: 3
Requires-Python: >=3.7
